Metadata-Version: 1.1
Name: WardenBot
Version: 0.16
Summary: Bot only used for monitoring purpose
Home-page: https://dadard.fr:3000
Author: Florian Charpentier
Author-email: florian.charpentier@epita.fr
License: WTFPL
Platform: UNKNOWN
Classifier: Environment :: Web Environment
Classifier: Framework :: Flask
Classifier: Intended Audience :: Developers
Classifier: License :: Freeware
Classifier: Operating System :: OS Independent
Classifier: Programming Language :: Python
Classifier: Programming Language :: Python :: 3.6
Classifier: Topic :: Internet :: WWW/HTTP
Classifier: Topic :: Internet :: WWW/HTTP :: Dynamic Content
